{
  "version": "1",
  "mode": "tree",
  "precedence": "allow-overrides-reject",
  "default-action": "reject",
      "allow-dirs": [
    ".cargo",
    ".github",
    ".hooksmith",
    ".trunk",
    "apps",
    "config",
    "contracts",
    "crates",
    "docs",
    "examples",
    "hooks",
    "infra",
    "schemas",
    "scripts",
    "tests",
    "tools",
    "wit"
  ],
  "allow-files": [
    "README.md",
    "Cargo.toml",
    "rust-toolchain.toml",
    "rustfmt.toml",
    "clippy.toml",
    "deny.toml",
    "build.rs",
    ".gitignore",
    ".gitattributes",
    ".gitmodules",
    ".dockerignore",
    "Dockerfile",
    "docker-compose.yml",
    "docker-bake.hcl",
    "*.md"
  ],
  "subject": {
    "scope": "top-level"
  },
  "digest": {
    "algo": "sha256",
    "value": "fbffad34a5cc342647a2785d634590ef252a29a1c3a4a02d19c6474ddfb8a3dc"
  }
}
